examples/app_test/__init__.py
examples/app_test/app.py
examples/english/__init__.py
examples/english/english_experiment.py
examples/english/transformer_configs.py
hatespans/__init__.py
hatespans/algo/__init__.py
hatespans/algo/evaluation.py
hatespans/algo/hate_spans_model.py
hatespans/algo/language_modeling.py
hatespans/algo/language_modeling_utils.py
hatespans/algo/predict.py
hatespans/algo/preprocess.py
hatespans/algo/utils.py
hatespans/algo/custom_models/__init__.py
hatespans/algo/custom_models/models.py
hatespans/app/__init__.py
hatespans/app/hate_spans_app.py
hatespans/config/__init__.py
hatespans/config/global_args.py
hatespans/config/model_args.py
hatespans/config/utils.py
hate_spans-0.1.0b0.dist-info/LICENSE
hate_spans-0.1.0b0.dist-info/METADATA
hate_spans-0.1.0b0.dist-info/WHEEL
hate_spans-0.1.0b0.dist-info/top_level.txt
hate_spans-0.1.0b0.dist-info/RECORD
